ifcopenshell/__init__.py
ifcopenshell/_ifcopenshell_wrapper.so
ifcopenshell/entity_instance.py
ifcopenshell/file.py
ifcopenshell/guid.py
ifcopenshell/ifcopenshell_wrapper.py
ifcopenshell/main.py
ifcopenshell/template.py
ifcopenshell/validate.py
ifcopenshell/express/DocAttribute.csv
ifcopenshell/express/DocDefined.csv
ifcopenshell/express/DocEntity.csv
ifcopenshell/express/DocEntityAttributes.csv
ifcopenshell/express/DocEnumeration.csv
ifcopenshell/express/DocSelect.csv
ifcopenshell/express/README.txt
ifcopenshell/express/__init__.py
ifcopenshell/express/bootstrap.py
ifcopenshell/express/codegen.py
ifcopenshell/express/definitions.py
ifcopenshell/express/documentation.py
ifcopenshell/express/express.bnf
ifcopenshell/express/express_parser.py
ifcopenshell/express/header.py
ifcopenshell/express/implementation.py
ifcopenshell/express/mapping.py
ifcopenshell/express/nodes.py
ifcopenshell/express/schema.py
ifcopenshell/express/schema_class.py
ifcopenshell/express/templates.py
ifcopenshell/geom/__init__.py
ifcopenshell/geom/app.py
ifcopenshell/geom/code_editor_pane.py
ifcopenshell/geom/main.py
ifcopenshell/geom/occ_utils.py
ifcopenshell/util/__init__.py
ifcopenshell/util/attribute_4_to_2x3.json
ifcopenshell/util/class_4_to_2x3.json
ifcopenshell/util/date.py
ifcopenshell/util/element.py
ifcopenshell/util/entity_to_type_map_2x3.json
ifcopenshell/util/entity_to_type_map_4.json
ifcopenshell/util/geolocation.py
ifcopenshell/util/placement.py
ifcopenshell/util/pset.py
ifcopenshell/util/schema.py
ifcopenshell/util/selector.py
ifcopenshell/util/type.py
ifcopenshell/util/unit.py
ifcopenshell_hypeifc-0.6.2.dist-info/LICENSE
ifcopenshell_hypeifc-0.6.2.dist-info/METADATA
ifcopenshell_hypeifc-0.6.2.dist-info/WHEEL
ifcopenshell_hypeifc-0.6.2.dist-info/top_level.txt
ifcopenshell_hypeifc-0.6.2.dist-info/RECORD
