Metadata-Version: 2.1
Name: ifcopenshell-hypeifc
Version: 0.6.2
Summary: ifcopenshell
Home-page: https://github.com/IfcOpenShell/IfcOpenShell
Author: ifcopenshell authors
Author-email: author@example.com
License: UNKNOWN
Project-URL: Bug Tracker, https://github.com/IfcOpenShell/IfcOpenShell/issues
Platform: UNKNOWN
Classifier: Programming Language :: Python :: 3.8
Classifier: License :: OSI Approved :: GNU Lesser General Public License v3 (LGPLv3)
Classifier: Operating System :: OS Independent
Requires-Python: >=3.8
License-File: LICENSE
